quorum_data_py/__init__.py
quorum_data_py/_utils.py
quorum_data_py/converter.py
quorum_data_py/feed.py
quorum_data_py/trx_type.py
quorum_data_py/util.py
quorum_data_py-1.2.7.dist-info/LICENSE
quorum_data_py-1.2.7.dist-info/METADATA
quorum_data_py-1.2.7.dist-info/WHEEL
quorum_data_py-1.2.7.dist-info/top_level.txt
quorum_data_py-1.2.7.dist-info/RECORD
